debuglater/__init__.py
debuglater/cli.py
debuglater/ipython.py
debuglater/pydump.py
debuglater-1.4.4.dist-info/LICENSE
debuglater-1.4.4.dist-info/METADATA
debuglater-1.4.4.dist-info/WHEEL
debuglater-1.4.4.dist-info/entry_points.txt
debuglater-1.4.4.dist-info/top_level.txt
debuglater-1.4.4.dist-info/RECORD
