Metadata-Version: 2.1
Name: debuglater
Version: 1.4.4
Summary: Post-mortem debugging for Python programs
Home-page: https://github.com/ploomber/debuglater
Author: Ploomber
Author-email: contact@plooomber.io
License: MIT
Classifier: Development Status :: 4 - Beta
Classifier: Environment :: Console
Classifier: Intended Audience :: Developers
Classifier: License :: OSI Approved :: MIT License
Classifier: Natural Language :: English
Classifier: Operating System :: OS Independent
Classifier: Programming Language :: Python
Classifier: Topic :: Software Development :: Debuggers
License-File: LICENSE
Requires-Dist: colorama
Provides-Extra: all
Requires-Dist: dill ; extra == 'all'
Provides-Extra: dev
Requires-Dist: pytest ; extra == 'dev'
Requires-Dist: yapf ; extra == 'dev'
Requires-Dist: flake8 ; extra == 'dev'
Requires-Dist: invoke ; extra == 'dev'
Requires-Dist: twine ; extra == 'dev'
Requires-Dist: pkgmt ; extra == 'dev'
Requires-Dist: pandas ; extra == 'dev'
Requires-Dist: numpy ; extra == 'dev'
Requires-Dist: dill ; extra == 'dev'
